[{"name": "HSBC", "rank": "1", "previous_rank": "1", "value": "28472.15", "previous_value": "25364.17", "rating": "AAA+", "previous_rating": "AAA+", "country": "United Kingdom"}, {"name": "Bank of America", "rank": "2", "previous_rank": "2", "value": "26046.91", "previous_value": "21017.43", "rating": "AAA+", "previous_rating": "AAA", "country": "United States"}, {"name": "Santander", "rank": "3", "previous_rank": "4", "value": "25576.48", "previous_value": "10839.71", "rating": "AAA+", "previous_rating": "AA", "country": "Spain"}, {"name": "WELLS FARGO", "rank": "4", "previous_rank": "3", "value": "21915.51", "previous_value": "14507.95", "rating": "AA", "previous_rating": "AA", "country": "United States"}, {"name": "Citi", "rank": "5", "previous_rank": "7", "value": "14362.35", "previous_value": "9809.59", "rating": "A+", "previous_rating": "A", "country": "United States"}, {"name": "BNP Paribas", "rank": "6", "previous_rank": "8", "value": "14059.82", "previous_value": "9360.48", "rating": "AA", "previous_rating": "AA-", "country": "France"}, {"name": "Goldman Sachs", "rank": "7", "previous_rank": "17", "value": "13886.94", "previous_value": "6752.70", "rating": "AAA+", "previous_rating": "AAA-", "country": "United States"}, {"name": "Chase", "rank": "8", "previous_rank": "10", "value": "13399.83", "previous_value": "8746.50", "rating": "AA", "previous_rating": "A+", "country": "United States"}, {"name": "Bradesco", "rank": "9", "previous_rank": "12", "value": "13298.90", "previous_value": "7698.39", "rating": "AAA-", "previous_rating": "AA", "country": "Brazil"}, {"name": "Barclays", "rank": "10", "previous_rank": "14", "value": "13133.71", "previous_value": "7582.58", "rating": "AA", "previous_rating": "A-", "country": "United Kingdom"}, {"name": "American Express", "rank": "11", "previous_rank": "6", "value": "12737.04", "previous_value": "9944.48", "rating": "AA", "previous_rating": "AA", "country": "United States"}, {"name": "ICBC", "rank": "12", "previous_rank": "5", "value": "12082.77", "previous_value": "10030.96", "rating": "AA+", "previous_rating": "A+", "country": "China"}, {"name": "China Construction Bank", "rank": "13", "previous_rank": "9", "value": "12076.47", "previous_value": "9023.65", "rating": "AA+", "previous_rating": "AA", "country": "China"}, {"name": "JP Morgan", "rank": "14", "previous_rank": "11", "value": "11732.33", "previous_value": "8071.69", "rating": "AA-", "previous_rating": "AA-", "country": "United States"}, {"name": "Sberbank", "rank": "15", "previous_rank": "26", "value": "11729.35", "previous_value": "4530.63", "rating": "AA+", "previous_rating": "AA-", "country": "Russia"}, {"name": "Soci\u00e9t\u00e9 G\u00e9n\u00e9rale", "rank": "16", "previous_rank": "20", "value": "11580.24", "previous_value": "5852.23", "rating": "AA-", "previous_rating": "A-", "country": "France"}, {"name": "BBVA", "rank": "17", "previous_rank": "19", "value": "10727.47", "previous_value": "6007.54", "rating": "AA-", "previous_rating": "A+", "country": "Spain"}, {"name": "Deutsche Bank", "rank": "18", "previous_rank": "18", "value": "9862.18", "previous_value": "6702.50", "rating": "AA-", "previous_rating": "AA-", "country": "Germany"}, {"name": "Bank of China", "rank": "19", "previous_rank": "16", "value": "9615.32", "previous_value": "7052.78", "rating": "AA", "previous_rating": "AA", "country": "China"}, {"name": "Credit Suisse", "rank": "20", "previous_rank": "13", "value": "8430.03", "previous_value": "7668.20", "rating": "AA", "previous_rating": "AA+", "country": "Switzerland"}, {"name": "UniCredit", "rank": "21", "previous_rank": "31", "value": "8341.95", "previous_value": "3102.87", "rating": "A+", "previous_rating": "BBB", "country": "Italy"}, {"name": "UBS", "rank": "22", "previous_rank": "15", "value": "8261.11", "previous_value": "7568.00", "rating": "AA-", "previous_rating": "AA-", "country": "Switzerland"}, {"name": "Morgan Stanley", "rank": "23", "previous_rank": "25", "value": "7907.13", "previous_value": "4775.17", "rating": "A+", "previous_rating": "A+", "country": "United States"}, {"name": "Standard Chartered", "rank": "24", "previous_rank": "24", "value": "7332.49", "previous_value": "4779.99", "rating": "AAA-", "previous_rating": "AA+", "country": "United Kingdom"}, {"name": "Ita\u00fa", "rank": "25", "previous_rank": "22", "value": "6910.55", "previous_value": "5592.72", "rating": "AAA-", "previous_rating": "AA+", "country": "Brazil"}, {"name": "Banco do Brasil", "rank": "26", "previous_rank": "36", "value": "6662.27", "previous_value": "2864.05", "rating": "AA+", "previous_rating": "AA-", "country": "Brazil"}, {"name": "MUFG", "rank": "27", "previous_rank": "23", "value": "6392.83", "previous_value": "5444.54", "rating": "A+", "previous_rating": "A+", "country": "Japan"}, {"name": "Agricultural Bank of China", "rank": "28", "previous_rank": "-", "value": "6031.94", "previous_value": "-", "rating": "A+", "previous_rating": "-", "country": "China"}, {"name": "Rabobank", "rank": "29", "previous_rank": "41", "value": "5627.14", "previous_value": "2623.82", "rating": "AA+", "previous_rating": "A", "country": "Netherlands"}, {"name": "Intesa Sanpaolo", "rank": "30", "previous_rank": "21", "value": "5505.83", "previous_value": "5759.72", "rating": "A+", "previous_rating": "A", "country": "Italy"}, {"name": "TD", "rank": "31", "previous_rank": "30", "value": "5178.60", "previous_value": "3257.23", "rating": "AA+", "previous_rating": "AA-", "country": "Canada"}, {"name": "RBC", "rank": "32", "previous_rank": "28", "value": "5169.84", "previous_value": "4370.36", "rating": "AA", "previous_rating": "AA", "country": "Canada"}, {"name": "VISA", "rank": "33", "previous_rank": "35", "value": "5036.82", "previous_value": "2874.58", "rating": "AAA-", "previous_rating": "AA+", "country": "United States"}, {"name": "DZ BANK", "rank": "34", "previous_rank": "27", "value": "4953.16", "previous_value": "4474.75", "rating": "A", "previous_rating": "A", "country": "Germany"}, {"name": "Cr\u00e9dit Agricole", "rank": "35", "previous_rank": "38", "value": "4616.78", "previous_value": "2742.77", "rating": "A+", "previous_rating": "A+", "country": "France"}, {"name": "State Bank of India", "rank": "36", "previous_rank": "70", "value": "4550.69", "previous_value": "1447.74", "rating": "AA+", "previous_rating": "AA", "country": "India"}, {"name": "Nordea", "rank": "37", "previous_rank": "43", "value": "4509.12", "previous_value": "2528.09", "rating": "AA", "previous_rating": "A", "country": "Sweden"}, {"name": "National Australia Bank", "rank": "38", "previous_rank": "39", "value": "4073.25", "previous_value": "2673.41", "rating": "A+", "previous_rating": "A-", "country": "Australia"}, {"name": "U.S. Bank", "rank": "39", "previous_rank": "33", "value": "3777.37", "previous_value": "2932.55", "rating": "AA", "previous_rating": "AA-", "country": "United States"}, {"name": "Commerzbank", "rank": "40", "previous_rank": "61", "value": "3520.80", "previous_value": "1737.79", "rating": "A+", "previous_rating": "A+", "country": "Germany"}, {"name": "Commonwealth Bank", "rank": "41", "previous_rank": "45", "value": "3475.13", "previous_value": "2381.03", "rating": "AA+", "previous_rating": "A+", "country": "Australia"}, {"name": "SMFG", "rank": "42", "previous_rank": "29", "value": "3461.71", "previous_value": "3427.83", "rating": "A", "previous_rating": "A", "country": "Japan"}, {"name": "PNC", "rank": "43", "previous_rank": "60", "value": "3382.88", "previous_value": "1752.14", "rating": "AA-", "previous_rating": "A+", "country": "United States"}, {"name": "Westpac", "rank": "44", "previous_rank": "53", "value": "3279.94", "previous_value": "1935.96", "rating": "AA+", "previous_rating": "A+", "country": "Australia"}, {"name": "Bank of Communications", "rank": "45", "previous_rank": "47", "value": "3268.52", "previous_value": "2297.10", "rating": "AA", "previous_rating": "AA-", "country": "China"}, {"name": "ERSTE", "rank": "46", "previous_rank": "57", "value": "3228.65", "previous_value": "1869.59", "rating": "AA-", "previous_rating": "BBB", "country": "Austria"}, {"name": "\"la Caixa\"", "rank": "47", "previous_rank": "58", "value": "3189.00", "previous_value": "1777.69", "rating": "AA", "previous_rating": "A-", "country": "Spain"}, {"name": "MasterCard", "rank": "48", "previous_rank": "50", "value": "3185.74", "previous_value": "2055.90", "rating": "AA+", "previous_rating": "AA+", "country": "United States"}, {"name": "Groupe Banque Populaire", "rank": "49", "previous_rank": "51", "value": "2998.29", "previous_value": "2012.52", "rating": "A", "previous_rating": "BBB", "country": "France"}, {"name": "Groupe Caisse d'Epargne", "rank": "50", "previous_rank": "44", "value": "2996.07", "previous_value": "2446.00", "rating": "A-", "previous_rating": "BBB", "country": "France"}, {"name": "Cr\u00e9dit mutuel", "rank": "51", "previous_rank": "37", "value": "2955.46", "previous_value": "2788.88", "rating": "A-", "previous_rating": "BBB", "country": "France"}, {"name": "ANZ", "rank": "52", "previous_rank": "56", "value": "2873.18", "previous_value": "1883.00", "rating": "AA", "previous_rating": "AA-", "country": "Australia"}, {"name": "KBC", "rank": "53", "previous_rank": "64", "value": "2863.63", "previous_value": "1657.93", "rating": "BBB", "previous_rating": "BB", "country": "Belgium"}, {"name": "Royal Bank of Scotland", "rank": "54", "previous_rank": "42", "value": "2837.69", "previous_value": "2584.24", "rating": "A-", "previous_rating": "BB", "country": "United Kingdom"}, {"name": "Danske Bank", "rank": "55", "previous_rank": "71", "value": "2834.99", "previous_value": "1412.26", "rating": "A+", "previous_rating": "BB", "country": "Denmark"}, {"name": "Bank of Montreal", "rank": "56", "previous_rank": "54", "value": "2767.22", "previous_value": "1929.89", "rating": "A+", "previous_rating": "A+", "country": "Canada"}, {"name": "Capital One", "rank": "57", "previous_rank": "34", "value": "2757.96", "previous_value": "2913.27", "rating": "A", "previous_rating": "A+", "country": "United States"}, {"name": "Merrill Lynch", "rank": "58", "previous_rank": "63", "value": "2693.84", "previous_value": "1682.48", "rating": "A+", "previous_rating": "BBB", "country": "United States"}, {"name": "Natixis", "rank": "59", "previous_rank": "59", "value": "2614.94", "previous_value": "1753.49", "rating": "AA-", "previous_rating": "AA-", "country": "France"}, {"name": "State Street", "rank": "60", "previous_rank": "52", "value": "2598.17", "previous_value": "1952.89", "rating": "AA-", "previous_rating": "A", "country": "United States"}, {"name": "Lloyds", "rank": "61", "previous_rank": "40", "value": "2594.84", "previous_value": "2646.32", "rating": "A", "previous_rating": "AA-", "country": "United Kingdom"}, {"name": "Scotiabank", "rank": "62", "previous_rank": "46", "value": "2579.16", "previous_value": "2321.05", "rating": "A", "previous_rating": "A", "country": "Canada"}, {"name": "Mizuho Group", "rank": "63", "previous_rank": "32", "value": "2507.90", "previous_value": "3065.08", "rating": "A+", "previous_rating": "A", "country": "Japan"}, {"name": "The Bank of New York Mellon", "rank": "64", "previous_rank": "49", "value": "2476.54", "previous_value": "2114.60", "rating": "A+", "previous_rating": "A+", "country": "United States"}, {"name": "Hypo Vereinsbank", "rank": "65", "previous_rank": "158", "value": "2433.52", "previous_value": "585.60", "rating": "A", "previous_rating": "BBB", "country": "Italy"}, {"name": "National Bank of Greece", "rank": "66", "previous_rank": "84", "value": "2314.31", "previous_value": "1243.71", "rating": "AA-", "previous_rating": "BBB", "country": "Greece"}, {"name": "CIBC", "rank": "67", "previous_rank": "55", "value": "2254.61", "previous_value": "1890.62", "rating": "A+", "previous_rating": "A+", "country": "Canada"}, {"name": "China Merchants Bank", "rank": "68", "previous_rank": "74", "value": "2212.03", "previous_value": "1361.51", "rating": "AA-", "previous_rating": "A-", "country": "China"}, {"name": "ICICI Bank", "rank": "69", "previous_rank": "110", "value": "2163.70", "previous_value": "939.38", "rating": "AA-", "previous_rating": "A+", "country": "India"}, {"name": "BB&T", "rank": "70", "previous_rank": "66", "value": "2056.16", "previous_value": "1546.49", "rating": "AA", "previous_rating": "A+", "country": "United States"}, {"name": "SEB", "rank": "71", "previous_rank": "93", "value": "2039.09", "previous_value": "1125.06", "rating": "AA-", "previous_rating": "A", "country": "Sweden"}, {"name": "Blackstone", "rank": "72", "previous_rank": "91", "value": "1996.80", "previous_value": "1155.25", "rating": "A+", "previous_rating": "A+", "country": "United States"}, {"name": "DnB", "rank": "73", "previous_rank": "131", "value": "1964.27", "previous_value": "786.35", "rating": "A+", "previous_rating": "BBB", "country": "Norway"}, {"name": "Shanghai Pudong Development Bank", "rank": "74", "previous_rank": "114", "value": "1961.82", "previous_value": "917.89", "rating": "AA-", "previous_rating": "AA-", "country": "China"}, {"name": "Franklin Templeton Investments", "rank": "75", "previous_rank": "113", "value": "1908.10", "previous_value": "922.25", "rating": "AA-", "previous_rating": "A", "country": "United States"}, {"name": "China CITIC Bank", "rank": "76", "previous_rank": "101", "value": "1865.86", "previous_value": "1042.58", "rating": "A+", "previous_rating": "A-", "country": "China"}, {"name": "St George Bank", "rank": "77", "previous_rank": "98", "value": "1863.57", "previous_value": "1069.40", "rating": "AA-", "previous_rating": "AA-", "country": "Australia"}, {"name": "Unibanco", "rank": "78", "previous_rank": "68", "value": "1859.48", "previous_value": "1519.51", "rating": "A+", "previous_rating": "A", "country": "Brazil"}, {"name": "Macquarie", "rank": "79", "previous_rank": "116", "value": "1854.01", "previous_value": "908.32", "rating": "AA", "previous_rating": "A+", "country": "Australia"}, {"name": "Raiffeisen Bank", "rank": "80", "previous_rank": "78", "value": "1850.74", "previous_value": "1303.19", "rating": "A", "previous_rating": "BBB", "country": "Austria"}, {"name": "VTB", "rank": "81", "previous_rank": "76", "value": "1817.60", "previous_value": "1329.22", "rating": "A", "previous_rating": "A", "country": "Russia"}, {"name": "Nomura", "rank": "82", "previous_rank": "102", "value": "1766.81", "previous_value": "1013.67", "rating": "A-", "previous_rating": "A+", "country": "Japan"}, {"name": "Halifax", "rank": "83", "previous_rank": "80", "value": "1737.64", "previous_value": "1299.18", "rating": "BB", "previous_rating": "A-", "country": "United Kingdom"}, {"name": "SunTrust", "rank": "84", "previous_rank": "62", "value": "1723.62", "previous_value": "1721.07", "rating": "A+", "previous_rating": "AA-", "country": "United States"}, {"name": "LCL", "rank": "85", "previous_rank": "90", "value": "1718.33", "previous_value": "1161.06", "rating": "A", "previous_rating": "A", "country": "France"}, {"name": "Criteria CaixaCorp", "rank": "86", "previous_rank": "134", "value": "1691.60", "previous_value": "781.58", "rating": "AA", "previous_rating": "BBB", "country": "Spain"}, {"name": "Discover", "rank": "87", "previous_rank": "100", "value": "1689.82", "previous_value": "1043.30", "rating": "A-", "previous_rating": "B", "country": "United States"}, {"name": "Dexia", "rank": "88", "previous_rank": "69", "value": "1679.20", "previous_value": "1448.12", "rating": "A+", "previous_rating": "A", "country": "Belgium"}, {"name": "Isbank", "rank": "89", "previous_rank": "86", "value": "1661.70", "previous_value": "1208.07", "rating": "AA-", "previous_rating": "A", "country": "Turkey"}, {"name": "JPMorganChase", "rank": "90", "previous_rank": "67", "value": "1606.92", "previous_value": "1537.91", "rating": "AA", "previous_rating": "AA-", "country": "United States"}, {"name": "BlackRock", "rank": "91", "previous_rank": "-", "value": "1579.67", "previous_value": "-", "rating": "AA", "previous_rating": "-", "country": "United States"}, {"name": "Bank of China (Hong Kong)", "rank": "92", "previous_rank": "81", "value": "1550.15", "previous_value": "1289.84", "rating": "A+", "previous_rating": "A", "country": "China (Hong Kong)"}, {"name": "Western Union", "rank": "93", "previous_rank": "99", "value": "1542.21", "previous_value": "1052.89", "rating": "AA-", "previous_rating": "AA-", "country": "United States"}, {"name": "CLSA", "rank": "94", "previous_rank": "119", "value": "1523.47", "previous_value": "891.24", "rating": "A", "previous_rating": "A-", "country": "France"}, {"name": "DBS", "rank": "95", "previous_rank": "73", "value": "1519.83", "previous_value": "1362.43", "rating": "AA", "previous_rating": "AA", "country": "Singapore"}, {"name": "Hang Seng Bank", "rank": "96", "previous_rank": "94", "value": "1506.87", "previous_value": "1104.24", "rating": "AA-", "previous_rating": "A", "country": "China (Hong Kong)"}, {"name": "CIC", "rank": "97", "previous_rank": "85", "value": "1500.79", "previous_value": "1226.27", "rating": "A", "previous_rating": "A", "country": "France"}, {"name": "Ameriprise Financial", "rank": "98", "previous_rank": "96", "value": "1497.61", "previous_value": "1081.97", "rating": "A", "previous_rating": "A", "country": "United States"}, {"name": "Caixa Geral de Dep\u00f3sitos", "rank": "99", "previous_rank": "79", "value": "1479.59", "previous_value": "1300.40", "rating": "A+", "previous_rating": "BB", "country": "Portugal"}, {"name": "Calyon", "rank": "100", "previous_rank": "121", "value": "1478.25", "previous_value": "868.09", "rating": "A", "previous_rating": "A-", "country": "France"}]